{
  "type": "minecraft:crafting_shaped",
  "category": "misc",
  "group": "valhelsia_furniture:colored_mangrove_chair",
  "key": {
    "#": {
      "item": "minecraft:mangrove_planks"
    },
    "W": {
      "item": "minecraft:gray_wool"
    },
    "X": {
      "type": "valhelsia_core:platform_dependent",
      "fabric:type": "valhelsia_core:platform_dependent",
      "fabric_value": {
        "item": "minecraft:stick"
      },
      "forge_value": {
        "tag": "forge:rods/wooden"
      }
    }
  },
  "pattern": [
    "X  ",
    "#WW",
    "X X"
  ],
  "result": {
    "count": 2,
    "item": "valhelsia_furniture:gray_mangrove_chair"
  },
  "show_notification": true
}